chelydra/__init__.py
chelydra/backup.py
chelydra/version.py
chelydra/tools/__init__.py
chelydra/tools/compression.py
chelydra/tools/cryptography.py
chelydra/tools/directory.py
chelydra-0.0.10.dist-info/LICENSE
chelydra-0.0.10.dist-info/METADATA
chelydra-0.0.10.dist-info/WHEEL
chelydra-0.0.10.dist-info/top_level.txt
chelydra-0.0.10.dist-info/RECORD
